<?xml version="1.0" encoding="utf-8"?>
<TextureAtlas imagePath="gaming.png">
	<!-- Created with Adobe Animate version 19.0.0.326 -->
	<!-- http://www.adobe.com/products/animate.html -->
	<SubTexture name="cutscene40000" x="0" y="0" width="4" height="3" frameX="0" frameY="0" frameWidth="604" frameHeight="804"/>
	<SubTexture name="cutscene40001" x="4" y="0" width="0" height="0" frameX="0" frameY="0" frameWidth="604" frameHeight="804"/>
	<SubTexture name="cutscene40002" x="4" y="0" width="0" height="0" frameX="0" frameY="0" frameWidth="604" frameHeight="804"/>
	<SubTexture name="cutscene40003" x="4" y="0" width="0" height="0" frameX="0" frameY="0" frameWidth="604" frameHeight="804"/>
	<SubTexture name="cutscene40004" x="4" y="0" width="0" height="0" frameX="0" frameY="0" frameWidth="604" frameHeight="804"/>
	<SubTexture name="cutscene40005" x="4" y="0" width="0" height="0" frameX="0" frameY="0" frameWidth="604" frameHeight="804"/>
	<SubTexture name="cutscene40006" x="4" y="0" width="0" height="0" frameX="0" frameY="0" frameWidth="604" frameHeight="804"/>
	<SubTexture name="cutscene40007" x="4" y="0" width="0" height="0" frameX="0" frameY="0" frameWidth="604" frameHeight="804"/>
	<SubTexture name="cutscene40008" x="4" y="0" width="0" height="0" frameX="0" frameY="0" frameWidth="604" frameHeight="804"/>
	<SubTexture name="cutscene40009" x="4" y="0" width="0" height="0" frameX="0" frameY="0" frameWidth="604" frameHeight="804"/>
	<SubTexture name="cutscene40010" x="4" y="0" width="0" height="0" frameX="0" frameY="0" frameWidth="604" frameHeight="804"/>
	<SubTexture name="cutscene40011" x="4" y="0" width="0" height="0" frameX="0" frameY="0" frameWidth="604" frameHeight="804"/>
	<SubTexture name="cutscene40012" x="4" y="0" width="0" height="0" frameX="0" frameY="0" frameWidth="604" frameHeight="804"/>
	<SubTexture name="cutscene40013" x="4" y="0" width="0" height="0" frameX="0" frameY="0" frameWidth="604" frameHeight="804"/>
	<SubTexture name="cutscene40014" x="4" y="0" width="0" height="0" frameX="0" frameY="0" frameWidth="604" frameHeight="804"/>
	<SubTexture name="cutscene40015" x="4" y="0" width="0" height="0" frameX="0" frameY="0" frameWidth="604" frameHeight="804"/>
	<SubTexture name="cutscene40016" x="4" y="0" width="0" height="0" frameX="0" frameY="0" frameWidth="604" frameHeight="804"/>
	<SubTexture name="cutscene40017" x="4" y="0" width="0" height="0" frameX="0" frameY="0" frameWidth="604" frameHeight="804"/>
	<SubTexture name="cutscene40018" x="4" y="0" width="0" height="0" frameX="0" frameY="0" frameWidth="604" frameHeight="804"/>
	<SubTexture name="cutscene40019" x="4" y="0" width="0" height="0" frameX="0" frameY="0" frameWidth="604" frameHeight="804"/>
	<SubTexture name="cutscene40020" x="4" y="0" width="0" height="0" frameX="0" frameY="0" frameWidth="604" frameHeight="804"/>
	<SubTexture name="cutscene40021" x="4" y="0" width="0" height="0" frameX="0" frameY="0" frameWidth="604" frameHeight="804"/>
	<SubTexture name="cutscene40022" x="4" y="0" width="0" height="0" frameX="0" frameY="0" frameWidth="604" frameHeight="804"/>
	<SubTexture name="cutscene40023" x="4" y="0" width="0" height="0" frameX="0" frameY="0" frameWidth="604" frameHeight="804"/>
	<SubTexture name="cutscene40024" x="4" y="0" width="0" height="0" frameX="0" frameY="0" frameWidth="604" frameHeight="804"/>
	<SubTexture name="cutscene40025" x="4" y="0" width="0" height="0" frameX="0" frameY="0" frameWidth="604" frameHeight="804"/>
	<SubTexture name="cutscene40026" x="4" y="0" width="0" height="0" frameX="0" frameY="0" frameWidth="604" frameHeight="804"/>
	<SubTexture name="cutscene40027" x="4" y="0" width="0" height="0" frameX="0" frameY="0" frameWidth="604" frameHeight="804"/>
	<SubTexture name="cutscene40028" x="4" y="0" width="0" height="0" frameX="0" frameY="0" frameWidth="604" frameHeight="804"/>
	<SubTexture name="cutscene40029" x="4" y="0" width="0" height="0" frameX="0" frameY="0" frameWidth="604" frameHeight="804"/>
	<SubTexture name="cutscene40030" x="4" y="0" width="0" height="0" frameX="0" frameY="0" frameWidth="604" frameHeight="804"/>
	<SubTexture name="cutscene40031" x="4" y="0" width="0" height="0" frameX="0" frameY="0" frameWidth="604" frameHeight="804"/>
	<SubTexture name="cutscene40032" x="4" y="0" width="0" height="0" frameX="0" frameY="0" frameWidth="604" frameHeight="804"/>
	<SubTexture name="cutscene40033" x="4" y="0" width="0" height="0" frameX="0" frameY="0" frameWidth="604" frameHeight="804"/>
	<SubTexture name="cutscene40034" x="4" y="0" width="0" height="0" frameX="0" frameY="0" frameWidth="604" frameHeight="804"/>
	<SubTexture name="cutscene40035" x="4" y="0" width="0" height="0" frameX="0" frameY="0" frameWidth="604" frameHeight="804"/>
	<SubTexture name="cutscene40036" x="4" y="0" width="0" height="0" frameX="0" frameY="0" frameWidth="604" frameHeight="804"/>
	<SubTexture name="cutscene40037" x="4" y="0" width="0" height="0" frameX="0" frameY="0" frameWidth="604" frameHeight="804"/>
	<SubTexture name="cutscene40038" x="4" y="0" width="0" height="0" frameX="0" frameY="0" frameWidth="604" frameHeight="804"/>
	<SubTexture name="cutscene40039" x="4" y="0" width="0" height="0" frameX="0" frameY="0" frameWidth="604" frameHeight="804"/>
	<SubTexture name="cutscene40040" x="4" y="0" width="0" height="0" frameX="0" frameY="0" frameWidth="604" frameHeight="804"/>
	<SubTexture name="cutscene40041" x="4" y="0" width="0" height="0" frameX="0" frameY="0" frameWidth="604" frameHeight="804"/>
	<SubTexture name="cutscene40042" x="4" y="0" width="0" height="0" frameX="0" frameY="0" frameWidth="604" frameHeight="804"/>
	<SubTexture name="cutscene40043" x="4" y="0" width="0" height="0" frameX="0" frameY="0" frameWidth="604" frameHeight="804"/>
	<SubTexture name="cutscene40044" x="4" y="0" width="0" height="0" frameX="0" frameY="0" frameWidth="604" frameHeight="804"/>
	<SubTexture name="cutscene40045" x="4" y="0" width="0" height="0" frameX="0" frameY="0" frameWidth="604" frameHeight="804"/>
	<SubTexture name="cutscene40046" x="4" y="0" width="0" height="0" frameX="0" frameY="0" frameWidth="604" frameHeight="804"/>
	<SubTexture name="cutscene40047" x="4" y="0" width="0" height="0" frameX="0" frameY="0" frameWidth="604" frameHeight="804"/>
	<SubTexture name="cutscene40048" x="4" y="0" width="0" height="0" frameX="0" frameY="0" frameWidth="604" frameHeight="804"/>
	<SubTexture name="cutscene40049" x="4" y="0" width="0" height="0" frameX="0" frameY="0" frameWidth="604" frameHeight="804"/>
	<SubTexture name="cutscene40050" x="4" y="0" width="0" height="0" frameX="0" frameY="0" frameWidth="604" frameHeight="804"/>
	<SubTexture name="cutscene40051" x="4" y="0" width="0" height="0" frameX="0" frameY="0" frameWidth="604" frameHeight="804"/>
	<SubTexture name="cutscene40052" x="4" y="0" width="0" height="0" frameX="0" frameY="0" frameWidth="604" frameHeight="804"/>
	<SubTexture name="cutscene40053" x="4" y="0" width="0" height="0" frameX="0" frameY="0" frameWidth="604" frameHeight="804"/>
	<SubTexture name="cutscene40054" x="4" y="0" width="0" height="0" frameX="0" frameY="0" frameWidth="604" frameHeight="804"/>
	<SubTexture name="cutscene40055" x="4" y="0" width="0" height="0" frameX="0" frameY="0" frameWidth="604" frameHeight="804"/>
	<SubTexture name="cutscene40056" x="4" y="0" width="0" height="0" frameX="0" frameY="0" frameWidth="604" frameHeight="804"/>
	<SubTexture name="cutscene40057" x="4" y="0" width="0" height="0" frameX="0" frameY="0" frameWidth="604" frameHeight="804"/>
	<SubTexture name="cutscene40058" x="4" y="0" width="0" height="0" frameX="0" frameY="0" frameWidth="604" frameHeight="804"/>
	<SubTexture name="cutscene40059" x="4" y="0" width="0" height="0" frameX="0" frameY="0" frameWidth="604" frameHeight="804"/>
	<SubTexture name="cutscene40060" x="4" y="0" width="0" height="0" frameX="0" frameY="0" frameWidth="604" frameHeight="804"/>
	<SubTexture name="cutscene40061" x="4" y="0" width="0" height="0" frameX="0" frameY="0" frameWidth="604" frameHeight="804"/>
	<SubTexture name="cutscene40062" x="4" y="0" width="0" height="0" frameX="0" frameY="0" frameWidth="604" frameHeight="804"/>
	<SubTexture name="cutscene40063" x="4" y="0" width="0" height="0" frameX="0" frameY="0" frameWidth="604" frameHeight="804"/>
	<SubTexture name="cutscene40064" x="4" y="0" width="0" height="0" frameX="0" frameY="0" frameWidth="604" frameHeight="804"/>
	<SubTexture name="cutscene40065" x="4" y="0" width="0" height="0" frameX="0" frameY="0" frameWidth="604" frameHeight="804"/>
	<SubTexture name="cutscene40066" x="4" y="0" width="0" height="0" frameX="0" frameY="0" frameWidth="604" frameHeight="804"/>
	<SubTexture name="cutscene40067" x="4" y="0" width="0" height="0" frameX="0" frameY="0" frameWidth="604" frameHeight="804"/>
	<SubTexture name="cutscene40068" x="4" y="0" width="0" height="0" frameX="0" frameY="0" frameWidth="604" frameHeight="804"/>
	<SubTexture name="cutscene40069" x="4" y="0" width="0" height="0" frameX="0" frameY="0" frameWidth="604" frameHeight="804"/>
	<SubTexture name="cutscene40070" x="4" y="0" width="0" height="0" frameX="0" frameY="0" frameWidth="604" frameHeight="804"/>
	<SubTexture name="cutscene40071" x="4" y="0" width="0" height="0" frameX="0" frameY="0" frameWidth="604" frameHeight="804"/>
	<SubTexture name="cutscene40072" x="4" y="0" width="0" height="0" frameX="0" frameY="0" frameWidth="604" frameHeight="804"/>
	<SubTexture name="cutscene40073" x="4" y="0" width="0" height="0" frameX="0" frameY="0" frameWidth="604" frameHeight="804"/>
	<SubTexture name="cutscene40074" x="4" y="0" width="0" height="0" frameX="0" frameY="0" frameWidth="604" frameHeight="804"/>
	<SubTexture name="cutscene40075" x="4" y="0" width="0" height="0" frameX="0" frameY="0" frameWidth="604" frameHeight="804"/>
	<SubTexture name="cutscene40076" x="4" y="0" width="0" height="0" frameX="0" frameY="0" frameWidth="604" frameHeight="804"/>
	<SubTexture name="cutscene40077" x="4" y="0" width="0" height="0" frameX="0" frameY="0" frameWidth="604" frameHeight="804"/>
	<SubTexture name="cutscene40078" x="4" y="0" width="0" height="0" frameX="0" frameY="0" frameWidth="604" frameHeight="804"/>
	<SubTexture name="cutscene40079" x="4" y="0" width="0" height="0" frameX="0" frameY="0" frameWidth="604" frameHeight="804"/>
	<SubTexture name="cutscene40080" x="4" y="0" width="0" height="0" frameX="0" frameY="0" frameWidth="604" frameHeight="804"/>
	<SubTexture name="cutscene40081" x="4" y="0" width="0" height="0" frameX="0" frameY="0" frameWidth="604" frameHeight="804"/>
	<SubTexture name="cutscene40082" x="4" y="0" width="0" height="0" frameX="0" frameY="0" frameWidth="604" frameHeight="804"/>
	<SubTexture name="cutscene40083" x="4" y="0" width="0" height="0" frameX="0" frameY="0" frameWidth="604" frameHeight="804"/>
	<SubTexture name="cutscene40084" x="4" y="0" width="0" height="0" frameX="0" frameY="0" frameWidth="604" frameHeight="804"/>
	<SubTexture name="cutscene40085" x="4" y="0" width="0" height="0" frameX="0" frameY="0" frameWidth="604" frameHeight="804"/>
	<SubTexture name="cutscene40086" x="4" y="0" width="0" height="0" frameX="0" frameY="0" frameWidth="604" frameHeight="804"/>
	<SubTexture name="cutscene40087" x="4" y="0" width="0" height="0" frameX="0" frameY="0" frameWidth="604" frameHeight="804"/>
	<SubTexture name="cutscene40088" x="4" y="0" width="0" height="0" frameX="0" frameY="0" frameWidth="604" frameHeight="804"/>
	<SubTexture name="cutscene40089" x="4" y="0" width="0" height="0" frameX="0" frameY="0" frameWidth="604" frameHeight="804"/>
	<SubTexture name="cutscene40090" x="4" y="0" width="0" height="0" frameX="0" frameY="0" frameWidth="604" frameHeight="804"/>
	<SubTexture name="cutscene40091" x="4" y="0" width="0" height="0" frameX="0" frameY="0" frameWidth="604" frameHeight="804"/>
	<SubTexture name="cutscene40092" x="4" y="0" width="0" height="0" frameX="0" frameY="0" frameWidth="604" frameHeight="804"/>
	<SubTexture name="cutscene40093" x="4" y="0" width="0" height="0" frameX="0" frameY="0" frameWidth="604" frameHeight="804"/>
	<SubTexture name="cutscene40094" x="4" y="0" width="0" height="0" frameX="0" frameY="0" frameWidth="604" frameHeight="804"/>
	<SubTexture name="cutscene40095" x="4" y="0" width="0" height="0" frameX="0" frameY="0" frameWidth="604" frameHeight="804"/>
	<SubTexture name="cutscene40096" x="4" y="0" width="0" height="0" frameX="0" frameY="0" frameWidth="604" frameHeight="804"/>
	<SubTexture name="cutscene40097" x="4" y="0" width="0" height="0" frameX="0" frameY="0" frameWidth="604" frameHeight="804"/>
	<SubTexture name="cutscene40098" x="4" y="0" width="0" height="0" frameX="0" frameY="0" frameWidth="604" frameHeight="804"/>
	<SubTexture name="cutscene40099" x="4" y="0" width="0" height="0" frameX="0" frameY="0" frameWidth="604" frameHeight="804"/>
	<SubTexture name="cutscene40100" x="4" y="0" width="0" height="0" frameX="0" frameY="0" frameWidth="604" frameHeight="804"/>
	<SubTexture name="cutscene40101" x="4" y="0" width="0" height="0" frameX="0" frameY="0" frameWidth="604" frameHeight="804"/>
	<SubTexture name="cutscene40102" x="4" y="0" width="0" height="0" frameX="0" frameY="0" frameWidth="604" frameHeight="804"/>
	<SubTexture name="cutscene40103" x="4" y="0" width="0" height="0" frameX="0" frameY="0" frameWidth="604" frameHeight="804"/>
	<SubTexture name="cutscene40104" x="4" y="0" width="0" height="0" frameX="0" frameY="0" frameWidth="604" frameHeight="804"/>
	<SubTexture name="cutscene40105" x="4" y="0" width="0" height="0" frameX="0" frameY="0" frameWidth="604" frameHeight="804"/>
	<SubTexture name="cutscene40106" x="4" y="0" width="0" height="0" frameX="0" frameY="0" frameWidth="604" frameHeight="804"/>
	<SubTexture name="cutscene40107" x="4" y="0" width="0" height="0" frameX="0" frameY="0" frameWidth="604" frameHeight="804"/>
	<SubTexture name="cutscene40108" x="4" y="0" width="0" height="0" frameX="0" frameY="0" frameWidth="604" frameHeight="804"/>
	<SubTexture name="cutscene40109" x="4" y="0" width="0" height="0" frameX="0" frameY="0" frameWidth="604" frameHeight="804"/>
	<SubTexture name="cutscene40110" x="4" y="0" width="0" height="0" frameX="0" frameY="0" frameWidth="604" frameHeight="804"/>
	<SubTexture name="cutscene40111" x="4" y="0" width="0" height="0" frameX="0" frameY="0" frameWidth="604" frameHeight="804"/>
	<SubTexture name="cutscene40112" x="4" y="0" width="0" height="0" frameX="0" frameY="0" frameWidth="604" frameHeight="804"/>
	<SubTexture name="cutscene40113" x="4" y="0" width="0" height="0" frameX="0" frameY="0" frameWidth="604" frameHeight="804"/>
	<SubTexture name="cutscene40114" x="4" y="0" width="0" height="0" frameX="0" frameY="0" frameWidth="604" frameHeight="804"/>
	<SubTexture name="cutscene40115" x="4" y="0" width="0" height="0" frameX="0" frameY="0" frameWidth="604" frameHeight="804"/>
	<SubTexture name="cutscene40116" x="4" y="0" width="0" height="0" frameX="0" frameY="0" frameWidth="604" frameHeight="804"/>
	<SubTexture name="cutscene40117" x="4" y="0" width="0" height="0" frameX="0" frameY="0" frameWidth="604" frameHeight="804"/>
	<SubTexture name="cutscene40118" x="4" y="0" width="0" height="0" frameX="0" frameY="0" frameWidth="604" frameHeight="804"/>
	<SubTexture name="cutscene40119" x="4" y="0" width="0" height="0" frameX="0" frameY="0" frameWidth="604" frameHeight="804"/>
	<SubTexture name="cutscene40120" x="4" y="0" width="0" height="0" frameX="0" frameY="0" frameWidth="604" frameHeight="804"/>
	<SubTexture name="cutscene40121" x="4" y="0" width="0" height="0" frameX="0" frameY="0" frameWidth="604" frameHeight="804"/>
	<SubTexture name="cutscene40122" x="4" y="0" width="0" height="0" frameX="0" frameY="0" frameWidth="604" frameHeight="804"/>
	<SubTexture name="cutscene40123" x="4" y="0" width="0" height="0" frameX="0" frameY="0" frameWidth="604" frameHeight="804"/>
	<SubTexture name="cutscene40124" x="4" y="0" width="0" height="0" frameX="0" frameY="0" frameWidth="604" frameHeight="804"/>
	<SubTexture name="cutscene40125" x="4" y="0" width="0" height="0" frameX="0" frameY="0" frameWidth="604" frameHeight="804"/>
	<SubTexture name="cutscene40126" x="4" y="0" width="0" height="0" frameX="0" frameY="0" frameWidth="604" frameHeight="804"/>
	<SubTexture name="cutscene40127" x="4" y="0" width="0" height="0" frameX="0" frameY="0" frameWidth="604" frameHeight="804"/>
	<SubTexture name="cutscene40128" x="4" y="0" width="0" height="0" frameX="0" frameY="0" frameWidth="604" frameHeight="804"/>
	<SubTexture name="cutscene40129" x="4" y="0" width="0" height="0" frameX="0" frameY="0" frameWidth="604" frameHeight="804"/>
	<SubTexture name="cutscene40130" x="4" y="0" width="0" height="0" frameX="0" frameY="0" frameWidth="604" frameHeight="804"/>
	<SubTexture name="cutscene40131" x="4" y="0" width="0" height="0" frameX="0" frameY="0" frameWidth="604" frameHeight="804"/>
	<SubTexture name="cutscene40132" x="4" y="0" width="0" height="0" frameX="0" frameY="0" frameWidth="604" frameHeight="804"/>
	<SubTexture name="cutscene40133" x="4" y="0" width="0" height="0" frameX="0" frameY="0" frameWidth="604" frameHeight="804"/>
	<SubTexture name="cutscene40134" x="4" y="0" width="0" height="0" frameX="0" frameY="0" frameWidth="604" frameHeight="804"/>
	<SubTexture name="cutscene40135" x="4" y="0" width="0" height="0" frameX="0" frameY="0" frameWidth="604" frameHeight="804"/>
	<SubTexture name="cutscene40136" x="4" y="0" width="0" height="0" frameX="0" frameY="0" frameWidth="604" frameHeight="804"/>
	<SubTexture name="cutscene40137" x="4" y="0" width="0" height="0" frameX="0" frameY="0" frameWidth="604" frameHeight="804"/>
	<SubTexture name="cutscene40138" x="4" y="0" width="0" height="0" frameX="0" frameY="0" frameWidth="604" frameHeight="804"/>
	<SubTexture name="cutscene40139" x="4" y="0" width="0" height="0" frameX="0" frameY="0" frameWidth="604" frameHeight="804"/>
	<SubTexture name="cutscene40140" x="4" y="0" width="0" height="0" frameX="0" frameY="0" frameWidth="604" frameHeight="804"/>
	<SubTexture name="cutscene40141" x="4" y="0" width="0" height="0" frameX="0" frameY="0" frameWidth="604" frameHeight="804"/>
	<SubTexture name="cutscene40142" x="4" y="0" width="0" height="0" frameX="0" frameY="0" frameWidth="604" frameHeight="804"/>
	<SubTexture name="cutscene40143" x="4" y="0" width="0" height="0" frameX="0" frameY="0" frameWidth="604" frameHeight="804"/>
	<SubTexture name="cutscene40144" x="4" y="0" width="0" height="0" frameX="0" frameY="0" frameWidth="604" frameHeight="804"/>
	<SubTexture name="cutscene40145" x="4" y="0" width="0" height="0" frameX="0" frameY="0" frameWidth="604" frameHeight="804"/>
	<SubTexture name="cutscene40146" x="4" y="0" width="0" height="0" frameX="0" frameY="0" frameWidth="604" frameHeight="804"/>
	<SubTexture name="cutscene40147" x="4" y="0" width="0" height="0" frameX="0" frameY="0" frameWidth="604" frameHeight="804"/>
	<SubTexture name="cutscene40148" x="4" y="0" width="0" height="0" frameX="0" frameY="0" frameWidth="604" frameHeight="804"/>
	<SubTexture name="cutscene40149" x="4" y="0" width="0" height="0" frameX="0" frameY="0" frameWidth="604" frameHeight="804"/>
	<SubTexture name="cutscene40150" x="4" y="0" width="0" height="0" frameX="0" frameY="0" frameWidth="604" frameHeight="804"/>
	<SubTexture name="cutscene40151" x="4" y="0" width="0" height="0" frameX="0" frameY="0" frameWidth="604" frameHeight="804"/>
	<SubTexture name="cutscene40152" x="4" y="0" width="0" height="0" frameX="0" frameY="0" frameWidth="604" frameHeight="804"/>
	<SubTexture name="cutscene40153" x="4" y="0" width="0" height="0" frameX="0" frameY="0" frameWidth="604" frameHeight="804"/>
	<SubTexture name="cutscene40154" x="4" y="0" width="0" height="0" frameX="0" frameY="0" frameWidth="604" frameHeight="804"/>
	<SubTexture name="cutscene40155" x="4" y="0" width="0" height="0" frameX="0" frameY="0" frameWidth="604" frameHeight="804"/>
	<SubTexture name="cutscene40156" x="4" y="0" width="0" height="0" frameX="0" frameY="0" frameWidth="604" frameHeight="804"/>
	<SubTexture name="cutscene40157" x="4" y="0" width="0" height="0" frameX="0" frameY="0" frameWidth="604" frameHeight="804"/>
	<SubTexture name="cutscene40158" x="4" y="0" width="0" height="0" frameX="0" frameY="0" frameWidth="604" frameHeight="804"/>
	<SubTexture name="cutscene40159" x="4" y="0" width="0" height="0" frameX="0" frameY="0" frameWidth="604" frameHeight="804"/>
	<SubTexture name="cutscene40160" x="4" y="0" width="0" height="0" frameX="0" frameY="0" frameWidth="604" frameHeight="804"/>
	<SubTexture name="cutscene40161" x="4" y="0" width="0" height="0" frameX="0" frameY="0" frameWidth="604" frameHeight="804"/>
	<SubTexture name="cutscene40162" x="4" y="0" width="0" height="0" frameX="0" frameY="0" frameWidth="604" frameHeight="804"/>
	<SubTexture name="cutscene40163" x="4" y="0" width="0" height="0" frameX="0" frameY="0" frameWidth="604" frameHeight="804"/>
	<SubTexture name="cutscene40164" x="4" y="0" width="0" height="0" frameX="0" frameY="0" frameWidth="604" frameHeight="804"/>
	<SubTexture name="cutscene40165" x="4" y="0" width="0" height="0" frameX="0" frameY="0" frameWidth="604" frameHeight="804"/>
	<SubTexture name="cutscene40166" x="4" y="0" width="0" height="0" frameX="0" frameY="0" frameWidth="604" frameHeight="804"/>
	<SubTexture name="cutscene40167" x="4" y="0" width="0" height="0" frameX="0" frameY="0" frameWidth="604" frameHeight="804"/>
	<SubTexture name="cutscene40168" x="4" y="0" width="0" height="0" frameX="0" frameY="0" frameWidth="604" frameHeight="804"/>
	<SubTexture name="cutscene40169" x="4" y="0" width="0" height="0" frameX="0" frameY="0" frameWidth="604" frameHeight="804"/>
	<SubTexture name="cutscene40170" x="4" y="0" width="0" height="0" frameX="0" frameY="0" frameWidth="604" frameHeight="804"/>
	<SubTexture name="cutscene40171" x="4" y="0" width="0" height="0" frameX="0" frameY="0" frameWidth="604" frameHeight="804"/>
	<SubTexture name="cutscene40172" x="4" y="0" width="0" height="0" frameX="0" frameY="0" frameWidth="604" frameHeight="804"/>
	<SubTexture name="cutscene40173" x="4" y="0" width="0" height="0" frameX="0" frameY="0" frameWidth="604" frameHeight="804"/>
	<SubTexture name="cutscene40174" x="4" y="0" width="0" height="0" frameX="0" frameY="0" frameWidth="604" frameHeight="804"/>
	<SubTexture name="cutscene40175" x="4" y="0" width="0" height="0" frameX="0" frameY="0" frameWidth="604" frameHeight="804"/>
	<SubTexture name="cutscene40176" x="4" y="0" width="0" height="0" frameX="0" frameY="0" frameWidth="604" frameHeight="804"/>
	<SubTexture name="cutscene40177" x="4" y="0" width="0" height="0" frameX="0" frameY="0" frameWidth="604" frameHeight="804"/>
	<SubTexture name="cutscene40178" x="4" y="0" width="0" height="0" frameX="0" frameY="0" frameWidth="604" frameHeight="804"/>
	<SubTexture name="cutscene40179" x="4" y="0" width="0" height="0" frameX="0" frameY="0" frameWidth="604" frameHeight="804"/>
	<SubTexture name="cutscene40180" x="4" y="0" width="0" height="0" frameX="0" frameY="0" frameWidth="604" frameHeight="804"/>
	<SubTexture name="cutscene40181" x="4" y="0" width="0" height="0" frameX="0" frameY="0" frameWidth="604" frameHeight="804"/>
	<SubTexture name="cutscene40182" x="4" y="0" width="0" height="0" frameX="0" frameY="0" frameWidth="604" frameHeight="804"/>
	<SubTexture name="cutscene40183" x="4" y="0" width="0" height="0" frameX="0" frameY="0" frameWidth="604" frameHeight="804"/>
	<SubTexture name="cutscene40184" x="4" y="0" width="0" height="0" frameX="0" frameY="0" frameWidth="604" frameHeight="804"/>
	<SubTexture name="cutscene40185" x="4" y="0" width="0" height="0" frameX="0" frameY="0" frameWidth="604" frameHeight="804"/>
	<SubTexture name="cutscene40186" x="4" y="0" width="0" height="0" frameX="0" frameY="0" frameWidth="604" frameHeight="804"/>
	<SubTexture name="cutscene40187" x="4" y="0" width="0" height="0" frameX="0" frameY="0" frameWidth="604" frameHeight="804"/>
	<SubTexture name="cutscene40188" x="4" y="0" width="0" height="0" frameX="0" frameY="0" frameWidth="604" frameHeight="804"/>
	<SubTexture name="cutscene40189" x="4" y="0" width="0" height="0" frameX="0" frameY="0" frameWidth="604" frameHeight="804"/>
	<SubTexture name="cutscene40190" x="4" y="0" width="0" height="0" frameX="0" frameY="0" frameWidth="604" frameHeight="804"/>
	<SubTexture name="cutscene40191" x="4" y="0" width="0" height="0" frameX="0" frameY="0" frameWidth="604" frameHeight="804"/>
	<SubTexture name="cutscene40192" x="4" y="0" width="0" height="0" frameX="0" frameY="0" frameWidth="604" frameHeight="804"/>
	<SubTexture name="cutscene40193" x="4" y="0" width="0" height="0" frameX="0" frameY="0" frameWidth="604" frameHeight="804"/>
	<SubTexture name="cutscene40194" x="4" y="0" width="0" height="0" frameX="0" frameY="0" frameWidth="604" frameHeight="804"/>
	<SubTexture name="cutscene40195" x="4" y="0" width="0" height="0" frameX="0" frameY="0" frameWidth="604" frameHeight="804"/>
	<SubTexture name="cutscene40196" x="4" y="0" width="0" height="0" frameX="0" frameY="0" frameWidth="604" frameHeight="804"/>
	<SubTexture name="cutscene40197" x="4" y="0" width="0" height="0" frameX="0" frameY="0" frameWidth="604" frameHeight="804"/>
	<SubTexture name="cutscene40198" x="4" y="0" width="0" height="0" frameX="0" frameY="0" frameWidth="604" frameHeight="804"/>
	<SubTexture name="cutscene40199" x="4" y="0" width="0" height="0" frameX="0" frameY="0" frameWidth="604" frameHeight="804"/>
	<SubTexture name="cutscene40200" x="4" y="0" width="0" height="0" frameX="0" frameY="0" frameWidth="604" frameHeight="804"/>
	<SubTexture name="cutscene40201" x="4" y="0" width="0" height="0" frameX="0" frameY="0" frameWidth="604" frameHeight="804"/>
	<SubTexture name="cutscene40202" x="4" y="0" width="0" height="0" frameX="0" frameY="0" frameWidth="604" frameHeight="804"/>
	<SubTexture name="cutscene40203" x="4" y="0" width="0" height="0" frameX="0" frameY="0" frameWidth="604" frameHeight="804"/>
	<SubTexture name="cutscene40204" x="4" y="0" width="0" height="0" frameX="0" frameY="0" frameWidth="604" frameHeight="804"/>
	<SubTexture name="cutscene40205" x="4" y="0" width="0" height="0" frameX="0" frameY="0" frameWidth="604" frameHeight="804"/>
	<SubTexture name="cutscene40206" x="4" y="0" width="0" height="0" frameX="0" frameY="0" frameWidth="604" frameHeight="804"/>
	<SubTexture name="cutscene40207" x="4" y="0" width="471" height="676" frameX="-133" frameY="-128" frameWidth="604" frameHeight="804"/>
	<SubTexture name="cutscene40208" x="4" y="0" width="471" height="676" frameX="-133" frameY="-128" frameWidth="604" frameHeight="804"/>
	<SubTexture name="cutscene40209" x="475" y="0" width="394" height="642" frameX="-185" frameY="-122" frameWidth="604" frameHeight="804"/>
	<SubTexture name="cutscene40210" x="475" y="0" width="394" height="642" frameX="-185" frameY="-122" frameWidth="604" frameHeight="804"/>
	<SubTexture name="cutscene40211" x="869" y="0" width="396" height="641" frameX="-191" frameY="-109" frameWidth="604" frameHeight="804"/>
	<SubTexture name="cutscene40212" x="869" y="0" width="396" height="641" frameX="-191" frameY="-109" frameWidth="604" frameHeight="804"/>
	<SubTexture name="cutscene40213" x="1265" y="0" width="390" height="634" frameX="-191" frameY="-111" frameWidth="604" frameHeight="804"/>
	<SubTexture name="cutscene40214" x="1265" y="0" width="390" height="634" frameX="-191" frameY="-111" frameWidth="604" frameHeight="804"/>
	<SubTexture name="cutscene40215" x="1265" y="0" width="390" height="634" frameX="-191" frameY="-111" frameWidth="604" frameHeight="804"/>
	<SubTexture name="cutscene40216" x="1265" y="0" width="390" height="634" frameX="-191" frameY="-111" frameWidth="604" frameHeight="804"/>
	<SubTexture name="cutscene40217" x="1265" y="0" width="390" height="634" frameX="-191" frameY="-111" frameWidth="604" frameHeight="804"/>
	<SubTexture name="cutscene40218" x="1265" y="0" width="390" height="634" frameX="-191" frameY="-111" frameWidth="604" frameHeight="804"/>
	<SubTexture name="cutscene40219" x="4" y="0" width="471" height="676" frameX="-133" frameY="-128" frameWidth="604" frameHeight="804"/>
	<SubTexture name="cutscene40220" x="4" y="0" width="471" height="676" frameX="-133" frameY="-128" frameWidth="604" frameHeight="804"/>
	<SubTexture name="cutscene40221" x="475" y="0" width="394" height="642" frameX="-185" frameY="-122" frameWidth="604" frameHeight="804"/>
	<SubTexture name="cutscene40222" x="475" y="0" width="394" height="642" frameX="-185" frameY="-122" frameWidth="604" frameHeight="804"/>
	<SubTexture name="cutscene40223" x="869" y="0" width="396" height="641" frameX="-191" frameY="-109" frameWidth="604" frameHeight="804"/>
	<SubTexture name="cutscene40224" x="869" y="0" width="396" height="641" frameX="-191" frameY="-109" frameWidth="604" frameHeight="804"/>
	<SubTexture name="cutscene40225" x="1265" y="0" width="390" height="634" frameX="-191" frameY="-111" frameWidth="604" frameHeight="804"/>
	<SubTexture name="cutscene40226" x="1265" y="0" width="390" height="634" frameX="-191" frameY="-111" frameWidth="604" frameHeight="804"/>
	<SubTexture name="cutscene40227" x="1265" y="0" width="390" height="634" frameX="-191" frameY="-111" frameWidth="604" frameHeight="804"/>
	<SubTexture name="cutscene40228" x="1265" y="0" width="390" height="634" frameX="-191" frameY="-111" frameWidth="604" frameHeight="804"/>
	<SubTexture name="cutscene40229" x="1265" y="0" width="390" height="634" frameX="-191" frameY="-111" frameWidth="604" frameHeight="804"/>
	<SubTexture name="cutscene40230" x="1265" y="0" width="390" height="634" frameX="-191" frameY="-111" frameWidth="604" frameHeight="804"/>
	<SubTexture name="cutscene40231" x="4" y="0" width="471" height="676" frameX="-133" frameY="-128" frameWidth="604" frameHeight="804"/>
	<SubTexture name="cutscene40232" x="4" y="0" width="471" height="676" frameX="-133" frameY="-128" frameWidth="604" frameHeight="804"/>
	<SubTexture name="cutscene40233" x="475" y="0" width="394" height="642" frameX="-185" frameY="-122" frameWidth="604" frameHeight="804"/>
	<SubTexture name="cutscene40234" x="475" y="0" width="394" height="642" frameX="-185" frameY="-122" frameWidth="604" frameHeight="804"/>
	<SubTexture name="cutscene40235" x="869" y="0" width="396" height="641" frameX="-191" frameY="-109" frameWidth="604" frameHeight="804"/>
	<SubTexture name="cutscene40236" x="869" y="0" width="396" height="641" frameX="-191" frameY="-109" frameWidth="604" frameHeight="804"/>
	<SubTexture name="cutscene40237" x="1265" y="0" width="390" height="634" frameX="-191" frameY="-111" frameWidth="604" frameHeight="804"/>
	<SubTexture name="cutscene40238" x="1265" y="0" width="390" height="634" frameX="-191" frameY="-111" frameWidth="604" frameHeight="804"/>
	<SubTexture name="cutscene40239" x="1265" y="0" width="390" height="634" frameX="-191" frameY="-111" frameWidth="604" frameHeight="804"/>
	<SubTexture name="cutscene40240" x="1265" y="0" width="390" height="634" frameX="-191" frameY="-111" frameWidth="604" frameHeight="804"/>
	<SubTexture name="cutscene40241" x="1265" y="0" width="390" height="634" frameX="-191" frameY="-111" frameWidth="604" frameHeight="804"/>
	<SubTexture name="cutscene40242" x="1265" y="0" width="390" height="634" frameX="-191" frameY="-111" frameWidth="604" frameHeight="804"/>
	<SubTexture name="cutscene40243" x="4" y="0" width="471" height="676" frameX="-133" frameY="-128" frameWidth="604" frameHeight="804"/>
	<SubTexture name="cutscene40244" x="4" y="0" width="471" height="676" frameX="-133" frameY="-128" frameWidth="604" frameHeight="804"/>
	<SubTexture name="cutscene40245" x="475" y="0" width="394" height="642" frameX="-185" frameY="-122" frameWidth="604" frameHeight="804"/>
	<SubTexture name="cutscene40246" x="475" y="0" width="394" height="642" frameX="-185" frameY="-122" frameWidth="604" frameHeight="804"/>
	<SubTexture name="cutscene40247" x="869" y="0" width="396" height="641" frameX="-191" frameY="-109" frameWidth="604" frameHeight="804"/>
	<SubTexture name="cutscene40248" x="869" y="0" width="396" height="641" frameX="-191" frameY="-109" frameWidth="604" frameHeight="804"/>
	<SubTexture name="cutscene40249" x="1265" y="0" width="390" height="634" frameX="-191" frameY="-111" frameWidth="604" frameHeight="804"/>
	<SubTexture name="cutscene40250" x="1265" y="0" width="390" height="634" frameX="-191" frameY="-111" frameWidth="604" frameHeight="804"/>
	<SubTexture name="cutscene40251" x="1265" y="0" width="390" height="634" frameX="-191" frameY="-111" frameWidth="604" frameHeight="804"/>
	<SubTexture name="cutscene40252" x="1265" y="0" width="390" height="634" frameX="-191" frameY="-111" frameWidth="604" frameHeight="804"/>
	<SubTexture name="cutscene40253" x="1265" y="0" width="390" height="634" frameX="-191" frameY="-111" frameWidth="604" frameHeight="804"/>
	<SubTexture name="cutscene40254" x="1265" y="0" width="390" height="634" frameX="-191" frameY="-111" frameWidth="604" frameHeight="804"/>
	<SubTexture name="cutscene40255" x="4" y="0" width="471" height="676" frameX="-133" frameY="-128" frameWidth="604" frameHeight="804"/>
	<SubTexture name="cutscene40256" x="4" y="0" width="471" height="676" frameX="-133" frameY="-128" frameWidth="604" frameHeight="804"/>
	<SubTexture name="cutscene40257" x="475" y="0" width="394" height="642" frameX="-185" frameY="-122" frameWidth="604" frameHeight="804"/>
	<SubTexture name="cutscene40258" x="475" y="0" width="394" height="642" frameX="-185" frameY="-122" frameWidth="604" frameHeight="804"/>
	<SubTexture name="cutscene40259" x="869" y="0" width="396" height="641" frameX="-191" frameY="-109" frameWidth="604" frameHeight="804"/>
	<SubTexture name="cutscene40260" x="869" y="0" width="396" height="641" frameX="-191" frameY="-109" frameWidth="604" frameHeight="804"/>
	<SubTexture name="cutscene40261" x="1265" y="0" width="390" height="634" frameX="-191" frameY="-111" frameWidth="604" frameHeight="804"/>
	<SubTexture name="cutscene40262" x="1265" y="0" width="390" height="634" frameX="-191" frameY="-111" frameWidth="604" frameHeight="804"/>
	<SubTexture name="cutscene40263" x="1265" y="0" width="390" height="634" frameX="-191" frameY="-111" frameWidth="604" frameHeight="804"/>
	<SubTexture name="cutscene40264" x="1265" y="0" width="390" height="634" frameX="-191" frameY="-111" frameWidth="604" frameHeight="804"/>
	<SubTexture name="cutscene40265" x="1265" y="0" width="390" height="634" frameX="-191" frameY="-111" frameWidth="604" frameHeight="804"/>
	<SubTexture name="cutscene40266" x="1265" y="0" width="390" height="634" frameX="-191" frameY="-111" frameWidth="604" frameHeight="804"/>
	<SubTexture name="cutscene40267" x="4" y="0" width="471" height="676" frameX="-133" frameY="-128" frameWidth="604" frameHeight="804"/>
	<SubTexture name="cutscene40268" x="4" y="0" width="471" height="676" frameX="-133" frameY="-128" frameWidth="604" frameHeight="804"/>
	<SubTexture name="cutscene40269" x="475" y="0" width="394" height="642" frameX="-185" frameY="-122" frameWidth="604" frameHeight="804"/>
	<SubTexture name="cutscene40270" x="475" y="0" width="394" height="642" frameX="-185" frameY="-122" frameWidth="604" frameHeight="804"/>
	<SubTexture name="cutscene40271" x="869" y="0" width="396" height="641" frameX="-191" frameY="-109" frameWidth="604" frameHeight="804"/>
	<SubTexture name="cutscene40272" x="869" y="0" width="396" height="641" frameX="-191" frameY="-109" frameWidth="604" frameHeight="804"/>
	<SubTexture name="cutscene40273" x="1265" y="0" width="390" height="634" frameX="-191" frameY="-111" frameWidth="604" frameHeight="804"/>
	<SubTexture name="cutscene40274" x="1265" y="0" width="390" height="634" frameX="-191" frameY="-111" frameWidth="604" frameHeight="804"/>
	<SubTexture name="cutscene40275" x="1265" y="0" width="390" height="634" frameX="-191" frameY="-111" frameWidth="604" frameHeight="804"/>
	<SubTexture name="cutscene40276" x="1265" y="0" width="390" height="634" frameX="-191" frameY="-111" frameWidth="604" frameHeight="804"/>
	<SubTexture name="cutscene40277" x="1265" y="0" width="390" height="634" frameX="-191" frameY="-111" frameWidth="604" frameHeight="804"/>
	<SubTexture name="cutscene40278" x="1265" y="0" width="390" height="634" frameX="-191" frameY="-111" frameWidth="604" frameHeight="804"/>
	<SubTexture name="cutscene40279" x="4" y="0" width="471" height="676" frameX="-133" frameY="-128" frameWidth="604" frameHeight="804"/>
	<SubTexture name="cutscene40280" x="4" y="0" width="471" height="676" frameX="-133" frameY="-128" frameWidth="604" frameHeight="804"/>
	<SubTexture name="cutscene40281" x="475" y="0" width="394" height="642" frameX="-185" frameY="-122" frameWidth="604" frameHeight="804"/>
	<SubTexture name="cutscene40282" x="475" y="0" width="394" height="642" frameX="-185" frameY="-122" frameWidth="604" frameHeight="804"/>
	<SubTexture name="cutscene40283" x="869" y="0" width="396" height="641" frameX="-191" frameY="-109" frameWidth="604" frameHeight="804"/>
	<SubTexture name="cutscene40284" x="869" y="0" width="396" height="641" frameX="-191" frameY="-109" frameWidth="604" frameHeight="804"/>
	<SubTexture name="cutscene40285" x="1265" y="0" width="390" height="634" frameX="-191" frameY="-111" frameWidth="604" frameHeight="804"/>
	<SubTexture name="cutscene40286" x="1265" y="0" width="390" height="634" frameX="-191" frameY="-111" frameWidth="604" frameHeight="804"/>
	<SubTexture name="cutscene40287" x="1265" y="0" width="390" height="634" frameX="-191" frameY="-111" frameWidth="604" frameHeight="804"/>
	<SubTexture name="cutscene40288" x="1265" y="0" width="390" height="634" frameX="-191" frameY="-111" frameWidth="604" frameHeight="804"/>
	<SubTexture name="cutscene40289" x="1265" y="0" width="390" height="634" frameX="-191" frameY="-111" frameWidth="604" frameHeight="804"/>
	<SubTexture name="cutscene40290" x="1265" y="0" width="390" height="634" frameX="-191" frameY="-111" frameWidth="604" frameHeight="804"/>
	<SubTexture name="cutscene40291" x="4" y="0" width="471" height="676" frameX="-133" frameY="-128" frameWidth="604" frameHeight="804"/>
	<SubTexture name="cutscene40292" x="4" y="0" width="471" height="676" frameX="-133" frameY="-128" frameWidth="604" frameHeight="804"/>
	<SubTexture name="cutscene40293" x="475" y="0" width="394" height="642" frameX="-185" frameY="-122" frameWidth="604" frameHeight="804"/>
	<SubTexture name="cutscene40294" x="475" y="0" width="394" height="642" frameX="-185" frameY="-122" frameWidth="604" frameHeight="804"/>
	<SubTexture name="cutscene40295" x="869" y="0" width="396" height="641" frameX="-191" frameY="-109" frameWidth="604" frameHeight="804"/>
	<SubTexture name="cutscene40296" x="869" y="0" width="396" height="641" frameX="-191" frameY="-109" frameWidth="604" frameHeight="804"/>
	<SubTexture name="cutscene40297" x="1265" y="0" width="390" height="634" frameX="-191" frameY="-111" frameWidth="604" frameHeight="804"/>
	<SubTexture name="cutscene40298" x="1265" y="0" width="390" height="634" frameX="-191" frameY="-111" frameWidth="604" frameHeight="804"/>
	<SubTexture name="cutscene40299" x="1265" y="0" width="390" height="634" frameX="-191" frameY="-111" frameWidth="604" frameHeight="804"/>
	<SubTexture name="cutscene40300" x="1265" y="0" width="390" height="634" frameX="-191" frameY="-111" frameWidth="604" frameHeight="804"/>
	<SubTexture name="cutscene40301" x="1265" y="0" width="390" height="634" frameX="-191" frameY="-111" frameWidth="604" frameHeight="804"/>
	<SubTexture name="cutscene40302" x="1265" y="0" width="390" height="634" frameX="-191" frameY="-111" frameWidth="604" frameHeight="804"/>
	<SubTexture name="cutscene40303" x="4" y="0" width="471" height="676" frameX="-133" frameY="-128" frameWidth="604" frameHeight="804"/>
	<SubTexture name="cutscene40304" x="4" y="0" width="471" height="676" frameX="-133" frameY="-128" frameWidth="604" frameHeight="804"/>
	<SubTexture name="cutscene40305" x="475" y="0" width="394" height="642" frameX="-185" frameY="-122" frameWidth="604" frameHeight="804"/>
	<SubTexture name="cutscene40306" x="475" y="0" width="394" height="642" frameX="-185" frameY="-122" frameWidth="604" frameHeight="804"/>
	<SubTexture name="cutscene40307" x="869" y="0" width="396" height="641" frameX="-191" frameY="-109" frameWidth="604" frameHeight="804"/>
	<SubTexture name="cutscene40308" x="869" y="0" width="396" height="641" frameX="-191" frameY="-109" frameWidth="604" frameHeight="804"/>
	<SubTexture name="cutscene40309" x="1265" y="0" width="390" height="634" frameX="-191" frameY="-111" frameWidth="604" frameHeight="804"/>
	<SubTexture name="cutscene40310" x="1265" y="0" width="390" height="634" frameX="-191" frameY="-111" frameWidth="604" frameHeight="804"/>
	<SubTexture name="cutscene40311" x="1265" y="0" width="390" height="634" frameX="-191" frameY="-111" frameWidth="604" frameHeight="804"/>
	<SubTexture name="cutscene40312" x="1265" y="0" width="390" height="634" frameX="-191" frameY="-111" frameWidth="604" frameHeight="804"/>
	<SubTexture name="cutscene40313" x="1265" y="0" width="390" height="634" frameX="-191" frameY="-111" frameWidth="604" frameHeight="804"/>
	<SubTexture name="cutscene40314" x="1265" y="0" width="390" height="634" frameX="-191" frameY="-111" frameWidth="604" frameHeight="804"/>
	<SubTexture name="cutscene40315" x="4" y="0" width="471" height="676" frameX="-133" frameY="-128" frameWidth="604" frameHeight="804"/>
	<SubTexture name="cutscene40316" x="4" y="0" width="471" height="676" frameX="-133" frameY="-128" frameWidth="604" frameHeight="804"/>
	<SubTexture name="cutscene40317" x="475" y="0" width="394" height="642" frameX="-185" frameY="-122" frameWidth="604" frameHeight="804"/>
	<SubTexture name="cutscene40318" x="475" y="0" width="394" height="642" frameX="-185" frameY="-122" frameWidth="604" frameHeight="804"/>
	<SubTexture name="cutscene40319" x="869" y="0" width="396" height="641" frameX="-191" frameY="-109" frameWidth="604" frameHeight="804"/>
	<SubTexture name="cutscene40320" x="869" y="0" width="396" height="641" frameX="-191" frameY="-109" frameWidth="604" frameHeight="804"/>
	<SubTexture name="cutscene40321" x="1265" y="0" width="390" height="634" frameX="-191" frameY="-111" frameWidth="604" frameHeight="804"/>
	<SubTexture name="cutscene40322" x="1265" y="0" width="390" height="634" frameX="-191" frameY="-111" frameWidth="604" frameHeight="804"/>
	<SubTexture name="cutscene40323" x="1265" y="0" width="390" height="634" frameX="-191" frameY="-111" frameWidth="604" frameHeight="804"/>
	<SubTexture name="cutscene40324" x="1265" y="0" width="390" height="634" frameX="-191" frameY="-111" frameWidth="604" frameHeight="804"/>
	<SubTexture name="cutscene40325" x="1265" y="0" width="390" height="634" frameX="-191" frameY="-111" frameWidth="604" frameHeight="804"/>
	<SubTexture name="cutscene40326" x="1265" y="0" width="390" height="634" frameX="-191" frameY="-111" frameWidth="604" frameHeight="804"/>
	<SubTexture name="cutscene40327" x="4" y="0" width="471" height="676" frameX="-133" frameY="-128" frameWidth="604" frameHeight="804"/>
	<SubTexture name="cutscene40328" x="4" y="0" width="471" height="676" frameX="-133" frameY="-128" frameWidth="604" frameHeight="804"/>
	<SubTexture name="cutscene40329" x="475" y="0" width="394" height="642" frameX="-185" frameY="-122" frameWidth="604" frameHeight="804"/>
	<SubTexture name="cutscene40330" x="475" y="0" width="394" height="642" frameX="-185" frameY="-122" frameWidth="604" frameHeight="804"/>
	<SubTexture name="cutscene40331" x="869" y="0" width="396" height="641" frameX="-191" frameY="-109" frameWidth="604" frameHeight="804"/>
	<SubTexture name="cutscene40332" x="869" y="0" width="396" height="641" frameX="-191" frameY="-109" frameWidth="604" frameHeight="804"/>
	<SubTexture name="cutscene40333" x="1265" y="0" width="390" height="634" frameX="-191" frameY="-111" frameWidth="604" frameHeight="804"/>
	<SubTexture name="cutscene40334" x="1265" y="0" width="390" height="634" frameX="-191" frameY="-111" frameWidth="604" frameHeight="804"/>
	<SubTexture name="cutscene40335" x="1265" y="0" width="390" height="634" frameX="-191" frameY="-111" frameWidth="604" frameHeight="804"/>
	<SubTexture name="cutscene40336" x="1265" y="0" width="390" height="634" frameX="-191" frameY="-111" frameWidth="604" frameHeight="804"/>
	<SubTexture name="cutscene40337" x="1265" y="0" width="390" height="634" frameX="-191" frameY="-111" frameWidth="604" frameHeight="804"/>
	<SubTexture name="cutscene40338" x="1265" y="0" width="390" height="634" frameX="-191" frameY="-111" frameWidth="604" frameHeight="804"/>
	<SubTexture name="cutscene40339" x="4" y="0" width="471" height="676" frameX="-133" frameY="-128" frameWidth="604" frameHeight="804"/>
	<SubTexture name="cutscene40340" x="4" y="0" width="471" height="676" frameX="-133" frameY="-128" frameWidth="604" frameHeight="804"/>
	<SubTexture name="cutscene40341" x="475" y="0" width="394" height="642" frameX="-185" frameY="-122" frameWidth="604" frameHeight="804"/>
	<SubTexture name="cutscene40342" x="475" y="0" width="394" height="642" frameX="-185" frameY="-122" frameWidth="604" frameHeight="804"/>
	<SubTexture name="cutscene40343" x="869" y="0" width="396" height="641" frameX="-191" frameY="-109" frameWidth="604" frameHeight="804"/>
	<SubTexture name="cutscene40344" x="869" y="0" width="396" height="641" frameX="-191" frameY="-109" frameWidth="604" frameHeight="804"/>
	<SubTexture name="cutscene40345" x="1265" y="0" width="390" height="634" frameX="-191" frameY="-111" frameWidth="604" frameHeight="804"/>
	<SubTexture name="cutscene40346" x="1265" y="0" width="390" height="634" frameX="-191" frameY="-111" frameWidth="604" frameHeight="804"/>
	<SubTexture name="cutscene40347" x="1265" y="0" width="390" height="634" frameX="-191" frameY="-111" frameWidth="604" frameHeight="804"/>
	<SubTexture name="cutscene40348" x="1265" y="0" width="390" height="634" frameX="-191" frameY="-111" frameWidth="604" frameHeight="804"/>
	<SubTexture name="cutscene40349" x="0" y="676" width="436" height="692" frameX="-154" frameY="-102" frameWidth="604" frameHeight="804"/>
	<SubTexture name="cutscene40350" x="0" y="676" width="436" height="692" frameX="-154" frameY="-102" frameWidth="604" frameHeight="804"/>
	<SubTexture name="cutscene40351" x="436" y="676" width="405" height="674" frameX="-175" frameY="-94" frameWidth="604" frameHeight="804"/>
	<SubTexture name="cutscene40352" x="436" y="676" width="405" height="674" frameX="-175" frameY="-94" frameWidth="604" frameHeight="804"/>
	<SubTexture name="cutscene40353" x="841" y="676" width="382" height="663" frameX="-191" frameY="-84" frameWidth="604" frameHeight="804"/>
	<SubTexture name="cutscene40354" x="841" y="676" width="382" height="663" frameX="-191" frameY="-84" frameWidth="604" frameHeight="804"/>
	<SubTexture name="cutscene40355" x="1223" y="676" width="382" height="661" frameX="-191" frameY="-86" frameWidth="604" frameHeight="804"/>
	<SubTexture name="cutscene40356" x="1223" y="676" width="382" height="661" frameX="-191" frameY="-86" frameWidth="604" frameHeight="804"/>
	<SubTexture name="cutscene40357" x="1605" y="676" width="382" height="664" frameX="-191" frameY="-86" frameWidth="604" frameHeight="804"/>
	<SubTexture name="cutscene40358" x="1605" y="676" width="382" height="664" frameX="-191" frameY="-86" frameWidth="604" frameHeight="804"/>
	<SubTexture name="cutscene40359" x="1605" y="676" width="382" height="664" frameX="-191" frameY="-86" frameWidth="604" frameHeight="804"/>
	<SubTexture name="cutscene40360" x="1605" y="676" width="382" height="664" frameX="-191" frameY="-86" frameWidth="604" frameHeight="804"/>
	<SubTexture name="cutscene40361" x="1605" y="676" width="382" height="664" frameX="-191" frameY="-86" frameWidth="604" frameHeight="804"/>
	<SubTexture name="cutscene40362" x="1605" y="676" width="382" height="664" frameX="-191" frameY="-86" frameWidth="604" frameHeight="804"/>
	<SubTexture name="cutscene40363" x="1605" y="676" width="382" height="664" frameX="-191" frameY="-86" frameWidth="604" frameHeight="804"/>
	<SubTexture name="cutscene40364" x="1605" y="676" width="382" height="664" frameX="-191" frameY="-86" frameWidth="604" frameHeight="804"/>
	<SubTexture name="cutscene40365" x="1605" y="676" width="382" height="664" frameX="-191" frameY="-86" frameWidth="604" frameHeight="804"/>
	<SubTexture name="cutscene40366" x="1605" y="676" width="382" height="664" frameX="-191" frameY="-86" frameWidth="604" frameHeight="804"/>
	<SubTexture name="cutscene40367" x="1605" y="676" width="382" height="664" frameX="-191" frameY="-86" frameWidth="604" frameHeight="804"/>
	<SubTexture name="cutscene40368" x="1605" y="676" width="382" height="664" frameX="-191" frameY="-86" frameWidth="604" frameHeight="804"/>
	<SubTexture name="cutscene40369" x="1605" y="676" width="382" height="664" frameX="-191" frameY="-86" frameWidth="604" frameHeight="804"/>
	<SubTexture name="cutscene40370" x="1605" y="676" width="382" height="664" frameX="-191" frameY="-86" frameWidth="604" frameHeight="804"/>
	<SubTexture name="cutscene40371" x="1605" y="676" width="382" height="664" frameX="-191" frameY="-86" frameWidth="604" frameHeight="804"/>
	<SubTexture name="cutscene40372" x="1605" y="676" width="382" height="664" frameX="-191" frameY="-86" frameWidth="604" frameHeight="804"/>
	<SubTexture name="cutscene40373" x="1605" y="676" width="382" height="664" frameX="-191" frameY="-86" frameWidth="604" frameHeight="804"/>
	<SubTexture name="cutscene40374" x="1605" y="676" width="382" height="664" frameX="-191" frameY="-86" frameWidth="604" frameHeight="804"/>
	<SubTexture name="cutscene40375" x="1605" y="676" width="382" height="664" frameX="-191" frameY="-86" frameWidth="604" frameHeight="804"/>
	<SubTexture name="cutscene40376" x="1605" y="676" width="382" height="664" frameX="-191" frameY="-86" frameWidth="604" frameHeight="804"/>
	<SubTexture name="cutscene40377" x="1605" y="676" width="382" height="664" frameX="-191" frameY="-86" frameWidth="604" frameHeight="804"/>
	<SubTexture name="cutscene40378" x="1605" y="676" width="382" height="664" frameX="-191" frameY="-86" frameWidth="604" frameHeight="804"/>
	<SubTexture name="cutscene40379" x="1605" y="676" width="382" height="664" frameX="-191" frameY="-86" frameWidth="604" frameHeight="804"/>
	<SubTexture name="cutscene40380" x="1605" y="676" width="382" height="664" frameX="-191" frameY="-86" frameWidth="604" frameHeight="804"/>
	<SubTexture name="cutscene40381" x="1605" y="676" width="382" height="664" frameX="-191" frameY="-86" frameWidth="604" frameHeight="804"/>
	<SubTexture name="cutscene40382" x="1605" y="676" width="382" height="664" frameX="-191" frameY="-86" frameWidth="604" frameHeight="804"/>
	<SubTexture name="cutscene40383" x="1605" y="676" width="382" height="664" frameX="-191" frameY="-86" frameWidth="604" frameHeight="804"/>
	<SubTexture name="cutscene40384" x="0" y="0" width="1" height="1" frameX="-5" frameY="-5" frameWidth="1" frameHeight="1"/>
</TextureAtlas>
